Metadata-Version: 2.1
Name: memformers
Version: 0.0.1
Summary: UNKNOWN
Home-page: https://github.com/qywu/memformers
Author: Qingyang Wu
Author-email: wilwu@ucdavis.edu
License: UNKNOWN
Platform: UNKNOWN
Classifier: Programming Language :: Python :: 3
Classifier: License :: OSI Approved :: MIT License
Classifier: Operating System :: OS Independent
